blazarclient/__init__.py
blazarclient/base.py
blazarclient/client.py
blazarclient/command.py
blazarclient/exception.py
blazarclient/i18n.py
blazarclient/shell.py
blazarclient/utils.py
blazarclient/version.py
blazarclient/osc/__init__.py
blazarclient/osc/plugin.py
blazarclient/tests/__init__.py
blazarclient/tests/test_base.py
blazarclient/tests/test_client.py
blazarclient/tests/test_command.py
blazarclient/tests/test_plugin.py
blazarclient/tests/test_shell.py
blazarclient/tests/v1/__init__.py
blazarclient/tests/v1/shell_commands/__init__.py
blazarclient/tests/v1/shell_commands/test_floatingips.py
blazarclient/tests/v1/shell_commands/test_hosts.py
blazarclient/tests/v1/shell_commands/test_leases.py
blazarclient/v1/__init__.py
blazarclient/v1/allocations.py
blazarclient/v1/client.py
blazarclient/v1/floatingips.py
blazarclient/v1/hosts.py
blazarclient/v1/leases.py
blazarclient/v1/shell_commands/__init__.py
blazarclient/v1/shell_commands/allocations.py
blazarclient/v1/shell_commands/floatingips.py
blazarclient/v1/shell_commands/hosts.py
blazarclient/v1/shell_commands/leases.py
python_blazarclient-4.4.0.dist-info/AUTHORS
python_blazarclient-4.4.0.dist-info/LICENSE
python_blazarclient-4.4.0.dist-info/METADATA
python_blazarclient-4.4.0.dist-info/WHEEL
python_blazarclient-4.4.0.dist-info/entry_points.txt
python_blazarclient-4.4.0.dist-info/pbr.json
python_blazarclient-4.4.0.dist-info/top_level.txt
python_blazarclient-4.4.0.dist-info/RECORD
